sklearn/__init__.py
sklearn/datasets/__init__.py
sklearn/datasets/make_regression.py
sklearn_beta-0.1.dist-info/METADATA
sklearn_beta-0.1.dist-info/WHEEL
sklearn_beta-0.1.dist-info/top_level.txt
sklearn_beta-0.1.dist-info/RECORD
